{
  "recipes": [
    {
      "id": 1,
      "name": "Feine Möhren-Kartoffel-Suppe",
      "description": "Ordner",
      "ingredients": [
        "Zwiebeln: 50g",
        "Kartoffeln: 500g",
        "Moehren: 350g",
        "Butter: 20g",
        "CremeFraiche: 150g",
        "Gemuesebruehe: 1000g"
      ],
      "instructions": [],
      "cookingTime": 0,
      "servings": 2,
      "difficulty": "medium",
      "category": "soup",
      "tags": ["soup", "potatoes", "day-to-day"]
    },
    {
      "id": 2,
      "name": "Himmel & Erde",
      "description": "Ordner",
      "ingredients": [
        "Kartoffeln: 600g",
        "Milch: 50g",
        "Butter: 25g",
        "Apfel: 600g",
        "Krakauer: 400g"
      ],
      "instructions": [],
      "cookingTime": 0,
      "servings": 4,
      "difficulty": "medium",
      "category": "potatoes",
      "tags": ["potatoes", "day-to-day"]
    },
    {
      "id": 3,
      "name": "Blaubeer Sommersalat",
      "description": "Ordner",
      "ingredients": [
        "Zucker: 20g",
        "Walknusskerne: 50g",
        "Salatblaetter: 200g",
        "Rucola: 50g",
        "Zwiebeln: 25g",
        "Heidelbeeren: 175g",
        "Feta: 120g",
        "Himbeeressig: 30g",
        "Honig: 10g",
        "Senf: 5g",
        "Walnussoel: 30g",
        "Salz: 2g",
        "Pfeffer: 2g"
      ],
      "instructions": [],
      "cookingTime": 0,
      "servings": 2,
      "difficulty": "medium",
      "category": "salad",
      "tags": ["salad", "day-to-day"]
    },
    {
      "id": 4,
      "name": "Grüne-Göttin-Salat",
      "description": "Plantiful Cooking, 25",
      "ingredients": [
        "Gurke: 500g",
        "Spitzkohl: 500g",
        "Petersilie: 10g",
        "Basilikum: 10g",
        "Dill: 10g",
        "Olivenoel: 30g",
        "Agavensirup: 10g",
        "Zitronenaft: 30g",
        "Salz: 3g",
        "Chiliflocken: 1g",
        "Cashewkerne: 25g"
      ],
      "instructions": [],
      "cookingTime": 0,
      "servings": 1,
      "difficulty": "medium",
      "category": "salad",
      "tags": ["salad", "day-to-day"]
    },
    {
      "id": 5,
      "name": "Grüne-Göttin-Salat mit Couscous",
      "description": "Plantiful Cooking, 25",
      "ingredients": [
        "Gurke: 500g",
        "Spitzkohl: 500g",
        "Petersilie: 10g",
        "Basilikum: 10g",
        "Dill: 10g",
        "Olivenoel: 30g",
        "Agavensirup: 10g",
        "Zitronenaft: 30g",
        "Salz: 3g",
        "Chiliflocken: 1g",
        "Cashewkerne: 25g",
        "Wasser: 450g",
        "Zitronenaft: 25g",
        "Salz: 1g",
        "Minze: 5g",
        "Couscous: 300g",
        "Tofu: 375g"
      ],
      "instructions": [],
      "cookingTime": 0,
      "servings": 4,
      "difficulty": "medium",
      "category": "salad",
      "tags": ["salad", "day-to-day"]
    },
    {
      "id": 6,
      "name": "Grüne-Göttin-Salat mit Tofu",
      "description": "Plantiful Cooking, 25",
      "ingredients": [
        "Gurke: 500g",
        "Spitzkohl: 500g",
        "Petersilie: 10g",
        "Basilikum: 10g",
        "Dill: 10g",
        "Olivenoel: 30g",
        "Agavensirup: 10g",
        "Zitronenaft: 30g",
        "Salz: 3g",
        "Chiliflocken: 1g",
        "Cashewkerne: 25g",
        "Tofu: 200g"
      ],
      "instructions": [],
      "cookingTime": 0,
      "servings": 2,
      "difficulty": "medium",
      "category": "salad",
      "tags": ["salad", "day-to-day"]
    },
    {
      "id": 7,
      "name": "Maple-Baked Salmon",
      "description": "You Suck At Cooking, 175",
      "ingredients": [
        "Olivenoel: 20g",
        "Ahornsirup: 20g",
        "Sojasosse: 7g",
        "Ingwer: 10g",
        "Lachs: 250g",
        "Reis: 120g",
        "Wasser: 240g"
      ],
      "instructions": [],
      "cookingTime": 0,
      "servings": 2,
      "difficulty": "medium",
      "category": "rice",
      "tags": ["rice", "day-to-day"]
    },
    {
      "id": 8,
      "name": "Blumenkohl \"Hack\"-Pide",
      "description": "Plantiful Cooking, 106",
      "ingredients": [
        "Mehl: 350g",
        "Trockenhefe: 4g",
        "Salz: 3g",
        "Olivenoel: 10g",
        "Blumenkohl: 300g",
        "Walknusskerne: 120g",
        "Champignons: 300g",
        "Olivenoel: 5g",
        "Salz: 2g",
        "Pfeffer: 0g",
        "Tomatenmark: 30g",
        "Paprikapulver: 2g",
        "Kreuzkuemmel: 2g",
        "Basilikum: 2g",
        "Zitronenaft: 25g",
        "Dattelsirup: 10g",
        "Petersilie: 10g",
        "Ahornsirup: 5g",
        "Sahne: 20g",
        "Tomate: 700g",
        "Petersilie: 40g",
        "Minze: 25g",
        "Paprika: 200g",
        "Olivenoel: 40g",
        "Harrisapaste: 5g",
        "Dattelsirup: 15g",
        "Zitronenaft: 40g",
        "Salz: 3g"
      ],
      "instructions": [],
      "cookingTime": 0,
      "servings": 5,
      "difficulty": "medium",
      "category": "other",
      "tags": ["day-to-day"]
    },
    {
      "id": 9,
      "name": "Torteletts Karotten + Walnüsse",
      "description": "Veg Box, 145",
      "ingredients": [
        "Blaetterteig: 230g",
        "Moehren: 350g",
        "Zwiebeln: 60g",
        "Fruehlingszwiebel: 150g",
        "Ahornsirup: 29g",
        "Balsamicoessig: 27g",
        "VeganerFrischkaese: 200g",
        "Walknusskerne: 50g"
      ],
      "instructions": [],
      "cookingTime": 0,
      "servings": 4,
      "difficulty": "medium",
      "category": "other",
      "tags": ["day-to-day"]
    },
    {
      "id": 10,
      "name": "Türkische Teigtaschen",
      "description": "Ordner",
      "ingredients": [],
      "instructions": [],
      "cookingTime": 0,
      "servings": 0,
      "difficulty": "medium",
      "category": "other",
      "tags": ["day-to-day"]
    },
    {
      "id": 11,
      "name": "Pita + Minze",
      "description": "Gruppe",
      "ingredients": [],
      "instructions": [],
      "cookingTime": 0,
      "servings": 0,
      "difficulty": "medium",
      "category": "other",
      "tags": ["day-to-day"]
    },
    {
      "id": 12,
      "name": "Hummus",
      "description": "Gruppe",
      "ingredients": [
        "Kichererbsen: 265g",
        "Zitronenaft: 50g",
        "Tahini: 60g",
        "Honig: 5g",
        "Kreuzkuemmel: 1g",
        "Paprikapulver: 1g",
        "Wasser: 50g",
        "Salz: 1g",
        "Pfeffer: 0g",
        "Olivenoel: 5g",
        "Schwarzkuemmel: 3g",
        "Petersilie: 5g"
      ],
      "instructions": [],
      "cookingTime": 0,
      "servings": 1,
      "difficulty": "medium",
      "category": "other",
      "tags": ["day-to-day"]
    },
    {
      "id": 13,
      "name": "Crispy Rice",
      "description": "PC, 38",
      "ingredients": [],
      "instructions": [],
      "cookingTime": 0,
      "servings": 0,
      "difficulty": "medium",
      "category": "other",
      "tags": ["day-to-day"]
    },
    {
      "id": 14,
      "name": "Wraps",
      "description": "",
      "ingredients": [],
      "instructions": [],
      "cookingTime": 0,
      "servings": 0,
      "difficulty": "medium",
      "category": "other",
      "tags": ["day-to-day"]
    },
    {
      "id": 15,
      "name": "Breakfast Sandwichest Med.",
      "description": "You Suck, 102",
      "ingredients": [],
      "instructions": [],
      "cookingTime": 0,
      "servings": 0,
      "difficulty": "medium",
      "category": "other",
      "tags": ["day-to-day"]
    },
    {
      "id": 16,
      "name": "Brokkoli-Schinken Quiche",
      "description": "Ordner",
      "ingredients": [
        "Mehl: 250g",
        "Salz: 1g",
        "Ei: 55g",
        "Butter: 125g",
        "Ei: 165g",
        "Parmesan: 50g",
        "Sahne: 200g",
        "Brokkoli: 600g",
        "Paprika: 200g",
        "Kochschinken: 100g",
        "Pfeffer: 0g",
        "Muskatnuss: 1g",
        "Salz: 3g"
      ],
      "instructions": [],
      "cookingTime": 0,
      "servings": 5,
      "difficulty": "medium",
      "category": "other",
      "tags": ["day-to-day"]
    },
    {
      "id": 17,
      "name": "Ziegenkäse-Quiche",
      "description": "Gruppe",
      "ingredients": [
        "Mehl: 250g",
        "Salz: 1g",
        "Paprikapulver: 1g",
        "Pfeffer: 0g",
        "Butter: 125g",
        "Wasser: 30g",
        "Butter: 2g",
        "Mehl: 10g",
        "Schmand: 200g",
        "Parmesan: 200g",
        "Ei: 220g",
        "Staerke: 20g",
        "Salz: 1g",
        "Pfeffer: 1g",
        "Paprikapulver: 1g",
        "Muskatnuss: 1g",
        "Tomate: 100g",
        "Ziegenfrischkaese: 150g"
      ],
      "instructions": [],
      "cookingTime": 0,
      "servings": 6,
      "difficulty": "medium",
      "category": "other",
      "tags": ["day-to-day"]
    },
    {
      "id": 18,
      "name": "Lauch-Hack-Suppe",
      "description": "Ordner",
      "ingredients": [],
      "instructions": [],
      "cookingTime": 0,
      "servings": 0,
      "difficulty": "medium",
      "category": "soup",
      "tags": ["soup", "day-to-day"]
    },
    {
      "id": 19,
      "name": "Pizzasuppe",
      "description": "Ordner",
      "ingredients": [],
      "instructions": [],
      "cookingTime": 0,
      "servings": 0,
      "difficulty": "medium",
      "category": "soup",
      "tags": ["soup", "day-to-day"]
    },
    {
      "id": 20,
      "name": "Marokkanische Karotten-Tajine",
      "description": "Veg Box, 152",
      "ingredients": [
        "Moehren: 500g",
        "GeschaelteTomate: 800g",
        "Zimt: 2g",
        "Paprikapulver: 4g",
        "Kreuzkuemmel: 8g",
        "Salz: 6g",
        "Kichererbsen: 400g",
        "Rosinen: 30g",
        "Mandel: 50g",
        "Reis: 240g",
        "Wasser: 480g"
      ],
      "instructions": [],
      "cookingTime": 0,
      "servings": 4,
      "difficulty": "medium",
      "category": "rice",
      "tags": ["rice", "day-to-day"]
    },
    {
      "id": 21,
      "name": "Spicy Peanut Butter Soup",
      "description": "You Suck, 133",
      "ingredients": [
        "Zwiebeln: 75g",
        "Olivenoel: 20g",
        "Gemuesebruehe: 1000g",
        "Brokkoli: 800g",
        "Moehren: 200g",
        "GeschaelteTomate: 400g",
        "Kichererbsen: 265g",
        "Erdnussmus: 150g",
        "BraunerZucker: 8g",
        "Salz: 8g",
        "Chiliflocken: 0g",
        "Pfeffer: 0g"
      ],
      "instructions": [],
      "cookingTime": 0,
      "servings": 3,
      "difficulty": "medium",
      "category": "soup",
      "tags": ["soup", "day-to-day"]
    },
    {
      "id": 22,
      "name": "Gefüllte Paprika",
      "description": "",
      "ingredients": [],
      "instructions": [],
      "cookingTime": 0,
      "servings": 0,
      "difficulty": "medium",
      "category": "other",
      "tags": ["day-to-day"]
    },
    {
      "id": 23,
      "name": "Kumpir",
      "description": "selfmade",
      "ingredients": [
        "Suesskartoffel: 700g",
        "Quark: 250g",
        "Hummus: 200g",
        "Salatblaetter: 100g",
        "Moehren: 100g",
        "Paprika: 100g",
        "Olivenoel: 20g",
        "Balsamicoessig: 10g"
      ],
      "instructions": [],
      "cookingTime": 0,
      "servings": 3,
      "difficulty": "medium",
      "category": "potatoes",
      "tags": ["potatoes", "day-to-day"]
    },
    {
      "id": 24,
      "name": "Ofengemüse",
      "description": "",
      "ingredients": [
        "Kartoffeln: 400g",
        "Suesskartoffel: 400g",
        "Aubergine: 200g",
        "Zucchini: 200g",
        "RoteBeete: 200g",
        "Moehren: 200g",
        "Paprika: 200g",
        "Feta: 200g",
        "Bohnenkraut: 2g",
        "Rosmarin: 2g",
        "Oregano: 2g",
        "Rapsoel: 50g",
        "Hummus: 175g",
        "Quark: 250g",
        "ItalienischeKrauter: 10g"
      ],
      "instructions": [],
      "cookingTime": 0,
      "servings": 4,
      "difficulty": "medium",
      "category": "potatoes",
      "tags": ["potatoes", "day-to-day"]
    },
    {
      "id": 25,
      "name": "Sesame-Roasted Broccoli",
      "description": "You Suck, 146",
      "ingredients": [
        "Brokkoli: 500g",
        "Olivenoel: 10g",
        "Sesamoel: 15g",
        "Sesam: 8g",
        "Salz: 3g",
        "Pfeffer: 0g"
      ],
      "instructions": [],
      "cookingTime": 0,
      "servings": 1,
      "difficulty": "medium",
      "category": "other",
      "tags": ["day-to-day"]
    },
    {
      "id": 26,
      "name": "Spitzkohl aus dem Ofen",
      "description": "Gruppe",
      "ingredients": [],
      "instructions": [],
      "cookingTime": 0,
      "servings": 0,
      "difficulty": "medium",
      "category": "other",
      "tags": ["day-to-day"]
    },
    {
      "id": 27,
      "name": "Sweet Potato Wedges",
      "description": "You Suck, 82",
      "ingredients": [],
      "instructions": [],
      "cookingTime": 0,
      "servings": 0,
      "difficulty": "medium",
      "category": "other",
      "tags": ["day-to-day"]
    },
    {
      "id": 28,
      "name": "Auberginen Bolognese",
      "description": "Gruppe",
      "ingredients": [
        "Aubergine: 750g",
        "Salz: 10g",
        "Zwiebeln: 75g",
        "Olivenoel: 30g",
        "Moehren: 250g",
        "Tomatenmark: 30g",
        "Rotwein: 100g",
        "Tomatenpueree: 800g",
        "Sojasosse: 30g",
        "Chiliflocken: 2g",
        "Ahornsirup: 2g",
        "Spaghetti: 400g",
        "Parmesan: 100g"
      ],
      "instructions": [],
      "cookingTime": 0,
      "servings": 5,
      "difficulty": "medium",
      "category": "noodles",
      "tags": ["noodles", "day-to-day"]
    },
    {
      "id": 29,
      "name": "Davids Spagetthi Carbonara",
      "description": "Ordner",
      "ingredients": [
        "Speckwuerfel: 50g",
        "Spaghetti: 175g",
        "Eigelb: 66g",
        "Sahne: 100g",
        "Parmesan: 50g",
        "Sahne: 1g",
        "Pfeffer: 0g"
      ],
      "instructions": [],
      "cookingTime": 0,
      "servings": 2,
      "difficulty": "medium",
      "category": "noodles",
      "tags": ["noodles", "sweet"]
    },
    {
      "id": 30,
      "name": "Eblipfanne",
      "description": "",
      "ingredients": [],
      "instructions": [],
      "cookingTime": 0,
      "servings": 0,
      "difficulty": "medium",
      "category": "other",
      "tags": ["day-to-day"]
    },
    {
      "id": 31,
      "name": "Veggie Rice Bowl",
      "description": "You Suck, 164",
      "ingredients": [
        "Reis: 110g",
        "Wasser: 220g",
        "Butter: 7g",
        "Ingwer: 10g",
        "Olivenoel: 30g",
        "Reisessig: 13g",
        "Honig: 9g",
        "Salz: 1g",
        "Sesamoel: 2g",
        "Gurke: 120g",
        "Moehren: 60g",
        "Paprika: 120g",
        "Avocado: 180g"
      ],
      "instructions": [],
      "cookingTime": 0,
      "servings": 2,
      "difficulty": "medium",
      "category": "rice",
      "tags": ["rice", "day-to-day"]
    },
    {
      "id": 32,
      "name": "Erdnuss-Tofu, Pak Choi",
      "description": "Veg Box, 164",
      "ingredients": [
        "Reis: 120g",
        "Wasser: 240g",
        "Fruehlingszwiebel: 20g",
        "PakChoi: 300g",
        "Tofu: 400g",
        "Erdnussmus: 70g",
        "Ahornsirup: 14g",
        "Sojasosse: 40g"
      ],
      "instructions": [],
      "cookingTime": 0,
      "servings": 3,
      "difficulty": "medium",
      "category": "rice",
      "tags": ["rice", "day-to-day"]
    },
    {
      "id": 33,
      "name": "Blueberry Smoothie",
      "description": "You Suck, 56",
      "ingredients": [
        "Heidelbeeren: 150g",
        "Milch: 375g",
        "Banane: 110g",
        "Erdnussmus: 60g"
      ],
      "instructions": [],
      "cookingTime": 0,
      "servings": 1,
      "difficulty": "medium",
      "category": "other",
      "tags": ["day-to-day"]
    },
    {
      "id": 34,
      "name": "Flammkuchen",
      "description": "",
      "ingredients": [
        "Tortillas: 186g",
        "Schmand: 100g",
        "Paprika: 50g",
        "Oliven: 10g",
        "Salz: 1g",
        "Pfeffer: 1g",
        "Oregano: 1g",
        "Birne: 100g",
        "Ziegenkaeserolle: 75g",
        "Honig: 10g",
        "Walknusskerne: 20g"
      ],
      "instructions": [],
      "cookingTime": 0,
      "servings": 2,
      "difficulty": "medium",
      "category": "other",
      "tags": ["day-to-day"]
    },
    {
      "id": 35,
      "name": "Antipasti Pizza",
      "description": "",
      "ingredients": [],
      "instructions": [],
      "cookingTime": 0,
      "servings": 0,
      "difficulty": "medium",
      "category": "other",
      "tags": ["day-to-day"]
    },
    {
      "id": 36,
      "name": "Parmigiana di Melanzane",
      "description": "Veg Box, 63",
      "ingredients": [],
      "instructions": [],
      "cookingTime": 0,
      "servings": 0,
      "difficulty": "medium",
      "category": "other",
      "tags": ["day-to-day"]
    },
    {
      "id": 37,
      "name": "Lasagne",
      "description": "Ordner",
      "ingredients": [
        "Olivenoel: 10g",
        "Hackfleisch: 500g",
        "Moehren: 200g",
        "Zwiebeln: 75g",
        "Petersilie: 40g",
        "Tomatenmark: 20g",
        "GeschaelteTomate: 800g",
        "Pfeffer: 1g",
        "Salz: 2g",
        "Milch: 500g",
        "Butter: 30g",
        "Mehl: 40g",
        "Salz: 1g",
        "Pfeffer: 0g",
        "Zitronenaft: 20g",
        "Muskatnuss: 2g",
        "Lasagneplatten: 175g",
        "GeriebenerKaese: 250g"
      ],
      "instructions": [],
      "cookingTime": 0,
      "servings": 6,
      "difficulty": "medium",
      "category": "noodles",
      "tags": ["noodles", "day-to-day"]
    },
    {
      "id": 38,
      "name": "Auberginen-Linsen-Auflauf",
      "description": "Veg Box, 61",
      "ingredients": [
        "Aubergine: 1000g",
        "Olivenoel: 30g",
        "Sojasosse: 18g",
        "Salz: 1g",
        "Moehren: 85g",
        "Olivenoel: 10g",
        "Salz: 0g",
        "Pfeffer: 0g",
        "BrauneLinsen: 265g",
        "Cheddar: 75g",
        "Tomate: 400g",
        "Olivenoel: 140g",
        "Mehl: 100g",
        "Milch: 1000g",
        "Salz: 1g",
        "Pfeffer: 1g",
        "Zitronenaft: 5g"
      ],
      "instructions": [],
      "cookingTime": 0,
      "servings": 6,
      "difficulty": "medium",
      "category": "other",
      "tags": ["day-to-day"]
    },
    {
      "id": 39,
      "name": "Shepherd's Pie",
      "description": "Gruppe",
      "ingredients": [
        "Kartoffeln: 800g",
        "Moehren: 300g",
        "Zwiebeln: 100g",
        "Hackfleisch: 500g",
        "BrauneLinsen: 265g",
        "Tomatenmark: 30g",
        "Erbsen: 100g",
        "Thymian: 5g",
        "Gemuesebruehe: 150g",
        "Worcestershiresauce: 10g",
        "Salz: 3g",
        "Pfeffer: 2g",
        "Milch: 125g",
        "Butter: 20g",
        "Muskatnuss: 2g",
        "Cheddar: 100g"
      ],
      "instructions": [],
      "cookingTime": 0,
      "servings": 5,
      "difficulty": "medium",
      "category": "potatoes",
      "tags": ["potatoes", "day-to-day"]
    },
    {
      "id": 40,
      "name": "Risotto mit Gorgonzola",
      "description": "Ordner",
      "ingredients": [
        "Zwiebeln: 50g",
        "Olivenoel: 10g",
        "Butter: 10g",
        "Risottoreis: 300g",
        "Weisswein: 50g",
        "Gemuesebruehe: 1000g",
        "Birne: 200g",
        "Gorgonzola: 150g",
        "Walknusskerne: 60g",
        "Petersilie: 15g",
        "Salz: 1g",
        "Pfeffer: 1g"
      ],
      "instructions": [],
      "cookingTime": 0,
      "servings": 4,
      "difficulty": "medium",
      "category": "rice",
      "tags": ["rice", "day-to-day"]
    },
    {
      "id": 41,
      "name": "Risotto + gegrillte Paprika",
      "description": "Ordner",
      "ingredients": [
        "Zwiebeln: 100g",
        "Paprika: 400g",
        "Rapsoel: 40g",
        "Risottoreis: 350g",
        "Gemuesebruehe: 1000g",
        "Zitronenaft: 10g",
        "Pfeffer: 1g",
        "Chiliflocken: 1g",
        "Frischkaese: 100g"
      ],
      "instructions": [],
      "cookingTime": 0,
      "servings": 4,
      "difficulty": "medium",
      "category": "rice",
      "tags": ["rice", "day-to-day"]
    },
    {
      "id": 42,
      "name": "Gemüserisotto",
      "description": "Gruppe",
      "ingredients": [
        "Zucchini: 1000g",
        "Olivenoel: 10g",
        "Salz: 3g",
        "Rosmarin: 6g",
        "Olivenoel: 20g",
        "Zwiebeln: 70g",
        "Risottoreis: 400g",
        "Weisswein: 125g",
        "Gemuesebruehe: 1000g",
        "Pfeffer: 1g",
        "Parmesan: 30g",
        "Rucola: 40g"
      ],
      "instructions": [],
      "cookingTime": 0,
      "servings": 4,
      "difficulty": "medium",
      "category": "rice",
      "tags": ["rice", "day-to-day"]
    },
    {
      "id": 43,
      "name": "Kichererbsensalat",
      "description": "Ordner",
      "ingredients": [
        "Kichererbsen: 265g",
        "Rapsoel: 10g",
        "Paprikapulver: 2g",
        "Salz: 0g",
        "Pfeffer: 0g",
        "Gurke: 350g",
        "Tomate: 250g",
        "Zwiebeln: 30g",
        "Feta: 200g",
        "Petersilie: 40g",
        "Balsamicoessig: 30g",
        "Olivenoel: 30g",
        "Honig: 9g",
        "Senf: 9g"
      ],
      "instructions": [],
      "cookingTime": 0,
      "servings": 2,
      "difficulty": "medium",
      "category": "salad",
      "tags": ["salad", "day-to-day"]
    },
    {
      "id": 44,
      "name": "Leos Linsensalat",
      "description": "Gruppe",
      "ingredients": [
        "Nudeln: 300g",
        "Wasser: 375g",
        "Belugalinsen: 125g",
        "Wasser: 200g",
        "Rucola: 125g",
        "Tomate: 100g",
        "GetrockneteTomaten: 50g",
        "Fruehlingszwiebel: 50g",
        "Zwiebeln: 70g",
        "Ziegenkaeserolle: 75g",
        "Honig: 7g",
        "Olivenoel: 25g",
        "Salz: 5g",
        "Pfeffer: 2g",
        "Majoran: 3g"
      ],
      "instructions": [],
      "cookingTime": 0,
      "servings": 4,
      "difficulty": "medium",
      "category": "salad",
      "tags": ["salad", "noodles", "day-to-day"]
    },
    {
      "id": 45,
      "name": "Crunchy Thai Peanut & Quinoa Salad",
      "description": "Gruppe",
      "ingredients": [
        "Quinoa: 130g",
        "Wasser: 360g",
        "Rotkohl: 140g",
        "Moehren: 100g",
        "Erbsen: 100g",
        "Erdnuesse: 35g",
        "Erdnussmus: 60g",
        "Sojasosse: 45g",
        "Ahornsirup: 20g",
        "Reisessig: 15g",
        "Sesamoel: 4g",
        "Ingwer: 5g",
        "Limettensaft: 20g",
        "Chiliflocken: 1g"
      ],
      "instructions": [],
      "cookingTime": 0,
      "servings": 2,
      "difficulty": "medium",
      "category": "salad",
      "tags": ["salad", "day-to-day"]
    },
    {
      "id": 46,
      "name": "Orientalischer Blumenkohl-Linsensalat",
      "description": "Gruppe",
      "ingredients": [
        "Belugalinsen: 300g",
        "Wasser: 600g",
        "Blumenkohl: 800g",
        "Zwiebeln: 70g",
        "Olivenoel: 80g",
        "RasElHanout: 3g",
        "Salz: 7g",
        "Pfeffer: 0g",
        "Cashewkerne: 100g",
        "Olivenoel: 80g",
        "Rosinen: 80g",
        "Zitronenaft: 70g",
        "Petersilie: 10g",
        "Minze: 8g",
        "Wasser: 160g",
        "Zitronenaft: 40g",
        "Agavensirup: 15g",
        "Sesamoel: 7g",
        "Cashewkerne: 100g",
        "Chiliflocken: 0g",
        "Sojasosse: 20g"
      ],
      "instructions": [],
      "cookingTime": 0,
      "servings": 7,
      "difficulty": "medium",
      "category": "salad",
      "tags": ["salad", "day-to-day"]
    },
    {
      "id": 47,
      "name": "Avocado-Ziegenkäse Salat",
      "description": "Ordner",
      "ingredients": [],
      "instructions": [],
      "cookingTime": 0,
      "servings": 0,
      "difficulty": "medium",
      "category": "salad",
      "tags": ["salad", "day-to-day"]
    },
    {
      "id": 48,
      "name": "Sweet Potato Salad",
      "description": "Ordner",
      "ingredients": [
        "Suesskartoffel: 500g",
        "Olivenoel: 10g",
        "Salz: 5g",
        "Spinat: 150g",
        "Zwiebeln: 40g",
        "Apfelessig: 25g",
        "Zitronenaft: 25g",
        "Cranberries: 50g",
        "Avocado: 120g",
        "Salz: 0g",
        "Pfeffer: 0g"
      ],
      "instructions": [],
      "cookingTime": 0,
      "servings": 2,
      "difficulty": "medium",
      "category": "salad",
      "tags": ["salad", "potatoes", "day-to-day"]
    },
    {
      "id": 49,
      "name": "Rote-Bete-Salat",
      "description": "Veg box, 78",
      "ingredients": [],
      "instructions": [],
      "cookingTime": 0,
      "servings": 0,
      "difficulty": "medium",
      "category": "salad",
      "tags": ["salad", "day-to-day"]
    },
    {
      "id": 50,
      "name": "Cauliflower Salad",
      "description": "Ordner",
      "ingredients": [
        "Blumenkohl: 850g",
        "Kichererbsen: 400g",
        "Olivenoel: 50g",
        "Chiliflocken: 1g",
        "Paprikapulver: 2g",
        "Pfeffer: 1g",
        "Salz: 2g",
        "Salatblaetter: 240g",
        "Gurke: 350g",
        "ItalienischeKrauter: 15g",
        "Feta: 125g",
        "Avocado: 250g",
        "Olivenoel: 50g",
        "Zitronenaft: 50g",
        "Senf: 30g",
        "Tahini: 50g",
        "Honig: 35g",
        "Apfelessig: 15g"
      ],
      "instructions": [],
      "cookingTime": 0,
      "servings": 5,
      "difficulty": "medium",
      "category": "salad",
      "tags": ["salad", "day-to-day"]
    },
    {
      "id": 51,
      "name": "Sommerrollen",
      "description": "",
      "ingredients": [],
      "instructions": [],
      "cookingTime": 0,
      "servings": 0,
      "difficulty": "medium",
      "category": "other",
      "tags": ["day-to-day"]
    },
    {
      "id": 52,
      "name": "Israelischer Salat",
      "description": "Ordner",
      "ingredients": [],
      "instructions": [],
      "cookingTime": 0,
      "servings": 0,
      "difficulty": "medium",
      "category": "salad",
      "tags": ["salad", "day-to-day"]
    },
    {
      "id": 53,
      "name": "Quinoa Salad",
      "description": "You Suck, 127",
      "ingredients": [
        "Quinoa: 200g",
        "Wasser: 400g",
        "Salz: 3g",
        "Olivenoel: 40g",
        "Balsamicoessig: 30g",
        "Ahornsirup: 5g",
        "Zwiebeln: 35g",
        "Kichererbsen: 265g",
        "Oliven: 110g",
        "Limettensaft: 10g",
        "Pfeffer: 0g"
      ],
      "instructions": [],
      "cookingTime": 0,
      "servings": 3,
      "difficulty": "medium",
      "category": "salad",
      "tags": ["salad", "day-to-day"]
    },
    {
      "id": 54,
      "name": "Zimtschnecke für 1",
      "description": "PC, 103",
      "ingredients": [
        "Mehl: 60g",
        "Backpulver: 5g",
        "Zucker: 10g",
        "Rapsoel: 10g",
        "Milch: 20g",
        "Zucker: 10g",
        "Zimt: 2g",
        "Zimt: 1g",
        "Butter: 7g",
        "Butter: 7g",
        "Puderzucker: 15g",
        "Milch: 3g"
      ],
      "instructions": [],
      "cookingTime": 0,
      "servings": 1,
      "difficulty": "medium",
      "category": "other",
      "tags": ["sweet"]
    },
    {
      "id": 55,
      "name": "Ofenkartoffeln mit Kräuterquark",
      "description": "",
      "ingredients": [
        "Kartoffeln: 600g",
        "Quark: 250g",
        "ItalienischeKrauter: 10g",
        "Salz: 1g",
        "Pfeffer: 1g"
      ],
      "instructions": [],
      "cookingTime": 0,
      "servings": 1,
      "difficulty": "medium",
      "category": "potatoes",
      "tags": ["potatoes", "day-to-day"]
    },
    {
      "id": 56,
      "name": "Acai-Bowl",
      "description": "selfmade",
      "ingredients": [
        "Walknusskerne: 40g",
        "Pistazien: 20g",
        "Himbeeren: 40g",
        "Heidelbeeren: 40g",
        "Brombeeren: 40g",
        "AcaiPueree: 100g",
        "Orange: 150g",
        "Banane: 150g",
        "Beerenmischung: 100g",
        "Vanilleextract: 2g",
        "Leinsamen: 20g"
      ],
      "instructions": [],
      "cookingTime": 0,
      "servings": 2,
      "difficulty": "medium",
      "category": "other",
      "tags": ["day-to-day"]
    },
    {
      "id": 57,
      "name": "Reibekuchen mit Apfelkompott",
      "description": "selfmade",
      "ingredients": [
        "Apfel: 250g",
        "Wasser: 20g",
        "Kartoffeln: 500g",
        "Zwiebeln: 50g",
        "Mehl: 20g",
        "Ei: 55g",
        "Salz: 4g",
        "Pfeffer: 0g",
        "Rapsoel: 40g"
      ],
      "instructions": [],
      "cookingTime": 0,
      "servings": 2,
      "difficulty": "medium",
      "category": "potatoes",
      "tags": ["potatoes", "day-to-day"]
    },
    {
      "id": 58,
      "name": "Onigirazu - Tofu-Chili-Mayo",
      "description": "PC, 20",
      "ingredients": [
        "Reis: 40g",
        "Wasser: 60g",
        "Salz: 1g",
        "Gurke: 50g",
        "Sesam: 7g",
        "Noriblatt: 3g",
        "Tofu: 70g",
        "Mayonnaise: 10g",
        "Srirachasauce: 5g",
        "Fruehlingszwiebel: 10g"
      ],
      "instructions": [],
      "cookingTime": 0,
      "servings": 1,
      "difficulty": "medium",
      "category": "rice",
      "tags": ["rice", "day-to-day"]
    },
    {
      "id": 59,
      "name": "Onigirazu - Tofu-Teriyaki",
      "description": "PC, 20",
      "ingredients": [
        "Reis: 40g",
        "Wasser: 60g",
        "Salz: 1g",
        "Gurke: 50g",
        "Sesam: 7g",
        "Noriblatt: 3g",
        "Tofu: 70g",
        "Teriyakisauce: 15g"
      ],
      "instructions": [],
      "cookingTime": 0,
      "servings": 1,
      "difficulty": "medium",
      "category": "rice",
      "tags": ["rice", "day-to-day"]
    },
    {
      "id": 60,
      "name": "Amerikanische Pancakes",
      "description": "Ordner",
      "ingredients": [
        "Ei: 110g",
        "Naturjoghurt: 150g",
        "Milch: 60g",
        "Backpulver: 8g",
        "Salz: 1g",
        "Mehl: 100g",
        "Kokosoel: 14g",
        "Ahornsirup: 40g",
        "Erdbeeren: 100g",
        "Heidelbeere: 50g",
        "Banane: 50g"
      ],
      "instructions": [],
      "cookingTime": 0,
      "servings": 2,
      "difficulty": "medium",
      "category": "other",
      "tags": ["day-to-day"]
    },
    {
      "id": 61,
      "name": "Karottensalat",
      "description": "selfmade",
      "ingredients": [
        "Moehren: 1000g",
        "Apfel: 300g",
        "Zitronenaft: 50g",
        "Zucker: 20g"
      ],
      "instructions": [],
      "cookingTime": 0,
      "servings": 1,
      "difficulty": "medium",
      "category": "salad",
      "tags": ["salad", "day-to-day"]
    },
    {
      "id": 62,
      "name": "Polentaauflauf mit Spinat",
      "description": "selfmade",
      "ingredients": [
        "Polenta: 300g",
        "Gemuesebruehe: 900g",
        "Olivenoel: 10g",
        "Muskatnuss: 1g",
        "Zwiebeln: 75g",
        "Pinienkerne: 20g",
        "Spinat: 500g",
        "Salz: 1g",
        "Pfeffer: 1g",
        "Muskatnuss: 3g",
        "Olivenoel: 10g",
        "Feta: 150g",
        "Tomate: 150g",
        "ItalienischeKrauter: 10g"
      ],
      "instructions": [],
      "cookingTime": 0,
      "servings": 3,
      "difficulty": "medium",
      "category": "other",
      "tags": ["day-to-day"]
    },
    {
      "id": 63,
      "name": "Karotten-Pistazien-Müsliriegel",
      "description": "Veg Box, 155",
      "ingredients": [
        "Moehren: 100g",
        "Pistazien: 100g",
        "Haferflocken: 200g",
        "Mehl: 75g",
        "Zucker: 125g",
        "Rapsoel: 150g",
        "Ahornsirup: 50g"
      ],
      "instructions": [],
      "cookingTime": 0,
      "servings": 6,
      "difficulty": "medium",
      "category": "other",
      "tags": ["sweet"]
    },
    {
      "id": 64,
      "name": "Goldene Müsliriegel",
      "description": "Yuka, 214 / Gruppe",
      "ingredients": [
        "Haferflocken: 50g",
        "Dattel: 150g",
        "Mandelmus: 80g",
        "Haselnusskerne: 150g",
        "GetrockneteAprikosen: 100g",
        "Sesam: 50g"
      ],
      "instructions": [],
      "cookingTime": 0,
      "servings": 4,
      "difficulty": "medium",
      "category": "other",
      "tags": ["sweet"]
    },
    {
      "id": 65,
      "name": "Kakao-Energy-Balls",
      "description": "Yuka, 220 / Gruppe",
      "ingredients": [
        "Dattel: 200g",
        "Vanilleextract: 5g",
        "Salz: 1g",
        "Mandel: 200g",
        "Erdnussmus: 40g",
        "Kakaopulver: 20g",
        "Sesam: 10g"
      ],
      "instructions": [],
      "cookingTime": 0,
      "servings": 4,
      "difficulty": "medium",
      "category": "other",
      "tags": ["sweet"]
    },
    {
      "id": 66,
      "name": "Gebackener Erdnuss-Tofu",
      "description": "PC, 32",
      "ingredients": [
        "Tofu: 400g",
        "Erdnussmus: 90g",
        "Limettensaft: 25g",
        "Knoblauchpulver: 2g",
        "Ingwerpulver: 1g",
        "Sojasosse: 25g",
        "Salz: 0g",
        "Agavensirup: 45g"
      ],
      "instructions": [],
      "cookingTime": 0,
      "servings": 2,
      "difficulty": "medium",
      "category": "other",
      "tags": ["day-to-day"]
    },
    {
      "id": 67,
      "name": "Zucchini-Pashtida",
      "description": "EatSmarter! 3/2024, 132",
      "ingredients": [
        "Zucchini: 400g",
        "Salz: 3g",
        "GriechischerJoghurt: 200g",
        "SaureSahne: 200g",
        "Ei: 180g",
        "Mehl: 15g",
        "Salz: 3g",
        "Pfeffer: 1g",
        "ItalienischeKrauter: 15g",
        "Feta: 150g",
        "Butter: 50g",
        "Filoteig: 125g",
        "Sesam: 10g"
      ],
      "instructions": [],
      "cookingTime": 0,
      "servings": 4,
      "difficulty": "medium",
      "category": "other",
      "tags": ["day-to-day"]
    },
    {
      "id": 68,
      "name": "Chinakohl-Apfel-Salat",
      "description": "selfmade",
      "ingredients": [
        "Chinakohl: 600g",
        "Apfel: 300g",
        "Sahne: 150g",
        "Salz: 1g",
        "Pfeffer: 0g",
        "Zucker: 3g",
        "Rapsoel: 15g",
        "Krauteressig: 12g"
      ],
      "instructions": [],
      "cookingTime": 0,
      "servings": 1,
      "difficulty": "medium",
      "category": "salad",
      "tags": ["salad", "day-to-day"]
    },
    {
      "id": 69,
      "name": "Spitzkohl aus dem Ofen",
      "description": "Gruppe",
      "ingredients": [
        "Spitzkohl: 1000g",
        "Olivenoel: 40g",
        "Kartoffeln: 500g",
        "Sahne: 200g",
        "Parmesan: 30g",
        "Salz: 2g",
        "Pfeffer: 1g"
      ],
      "instructions": [],
      "cookingTime": 0,
      "servings": 3,
      "difficulty": "medium",
      "category": "potatoes",
      "tags": ["potatoes", "day-to-day"]
    },
    {
      "id": 70,
      "name": "Lachs im Ofen mit Ofenkartoffeln",
      "description": "Gruppe",
      "ingredients": [
        "Lachs: 250g",
        "Olivenoel: 40g",
        "Salz: 5g",
        "Kartoffeln: 1000g",
        "Olivenoel: 40g",
        "Salz: 3g",
        "Dill: 10g",
        "Olivenoel: 10g",
        "Salz: 1g",
        "Pfeffer: 1g",
        "Zitronenaft: 10g"
      ],
      "instructions": [],
      "cookingTime": 0,
      "servings": 3,
      "difficulty": "medium",
      "category": "potatoes",
      "tags": ["potatoes", "day-to-day"]
    },
    {
      "id": 71,
      "name": "Salat mit gerösteten Kürbis und Feta",
      "description": "Gruppe",
      "ingredients": [
        "HokkaidoKuerbis: 500g",
        "Olivenoel: 40g",
        "Paprikapulver: 1g",
        "Olivenoel: 60g",
        "Krauteressig: 40g",
        "Senf: 5g",
        "Honig: 5g",
        "Rucola: 125g",
        "Feta: 200g",
        "Kuerbiskerne: 20g",
        "Salz: 2g",
        "Pfeffer: 1g"
      ],
      "instructions": [],
      "cookingTime": 0,
      "servings": 3,
      "difficulty": "medium",
      "category": "salad",
      "tags": ["salad", "day-to-day"]
    },
    {
      "id": 72,
      "name": "Spaghettikürbis mit Blattspinat und Feta aus dem Ofen",
      "description": "Gruppe",
      "ingredients": [
        "Spaghettikuerbis: 1000g",
        "Olivenoel: 20g",
        "Spinat: 250g",
        "Tomate: 50g",
        "Feta: 150g",
        "Sahne: 150g",
        "Salz: 2g",
        "Pfeffer: 1g",
        "Pinienkerne: 20g"
      ],
      "instructions": [],
      "cookingTime": 0,
      "servings": 2,
      "difficulty": "medium",
      "category": "other",
      "tags": ["day-to-day"]
    },
    {
      "id": 73,
      "name": "Gesunde Carrot Cake Energy Balls",
      "description": "Gruppe",
      "ingredients": [
        "Mandel: 50g",
        "Walknusskerne: 25g",
        "Moehren: 100g",
        "Dattel: 200g",
        "Kokosraspeln: 40g",
        "Ingwerpulver: 1g",
        "Zimt: 1g",
        "Salz: 1g"
      ],
      "instructions": [],
      "cookingTime": 0,
      "servings": 2,
      "difficulty": "medium",
      "category": "other",
      "tags": ["sweet"]
    },
    {
      "id": 74,
      "name": "Cremiges Gemüsegratin",
      "description": "Gruppe",
      "ingredients": [
        "Spitzkohl: 400g",
        "Brokkoli: 400g",
        "Olivenoel: 10g",
        "Salz: 3g",
        "Semmelbroesel: 75g",
        "Nudeln: 300g",
        "Erbsen: 200g",
        "Spinat: 250g",
        "Butter: 75g",
        "Mehl: 75g",
        "Milch: 750g",
        "Senf: 5g",
        "GeriebenerKaese: 200g",
        "Muskatnuss: 3g",
        "Pfeffer: 1g"
      ],
      "instructions": [],
      "cookingTime": 0,
      "servings": 6,
      "difficulty": "medium",
      "category": "noodles",
      "tags": ["noodles", "day-to-day"]
    },
    {
      "id": 75,
      "name": "Veggie-Moussaka",
      "description": "Gruppe",
      "ingredients": [
        "Kartoffeln: 500g",
        "Zwiebeln: 75g",
        "Thymian: 10g",
        "Salz: 2g",
        "Pfeffer: 1g",
        "Olivenoel: 70g",
        "Aubergine: 500g",
        "Zucchini: 400g",
        "Belugalinsen: 200g",
        "Zwiebeln: 75g",
        "Olivenoel: 10g",
        "Zimt: 1g",
        "Muskatnuss: 1g",
        "Gemuesebruehe: 120g",
        "gehackteTomaten: 400g",
        "Oregano: 2g",
        "Salz: 1g",
        "Pfeffer: 1g",
        "Butter: 70g",
        "Mehl: 70g",
        "Milch: 700g",
        "Muskatnuss: 3g",
        "Parmesan: 80g",
        "Feta: 50g"
      ],
      "instructions": [],
      "cookingTime": 0,
      "servings": 6,
      "difficulty": "medium",
      "category": "potatoes",
      "tags": ["potatoes", "day-to-day"]
    },
    {
      "id": 76,
      "name": "Kürbis-Kohl-Lasagne mit Pesto",
      "description": "Veg Box, 130",
      "ingredients": [
        "Gruenkohl: 200g",
        "Rapsoel: 10g",
        "Salz: 3g",
        "Pfeffer: 1g",
        "Lauch: 400g",
        "ButternutKuerbis: 500g",
        "gehackteTomaten: 400g",
        "Pesto: 100g",
        "Rapsoel: 70g",
        "Mehl: 70g",
        "Milch: 750g",
        "Cheddar: 25g",
        "Salz: 1g",
        "Pfeffer: 1g",
        "Lasagneplatten: 250g",
        "Semmelbroesel: 30g",
        "Rapsoel: 10g",
        "Cheddar: 75g"
      ],
      "instructions": [],
      "cookingTime": 0,
      "servings": 7,
      "difficulty": "medium",
      "category": "noodles",
      "tags": ["noodles", "day-to-day"]
    },
    {
      "id": 77,
      "name": "Aubergine mit Sesam-Couscous-Crumble",
      "description": "slowly veggie! 7, 80",
      "ingredients": [
        "Sesam: 40g",
        "Couscous: 125g",
        "Mehl: 30g",
        "Butter: 100g",
        "Salz: 1g",
        "Aubergine: 1000g",
        "Zwiebeln: 100g",
        "Chiliflocken: 1g",
        "Tomate: 400g",
        "Dattel: 50g",
        "Granatapfel: 250g",
        "Erdnussoel: 30g",
        "Gemuesebruehe: 200g",
        "Kreuzkuemmel: 3g"
      ],
      "instructions": [],
      "cookingTime": 0,
      "servings": 4,
      "difficulty": "medium",
      "category": "other",
      "tags": ["day-to-day"]
    },
    {
      "id": 78,
      "name": "Tomatensalat mit Thunfisch und Feta",
      "description": "eat smarter, 44",
      "ingredients": [
        "Tomate: 1000g",
        "Petersilie: 10g",
        "Thunfisch: 200g",
        "Feta: 200g",
        "Zwiebeln: 60g",
        "Olivenoel: 40g",
        "Krauteressig: 40g",
        "Honig: 10g",
        "Salz: 3g",
        "Pfeffer: 1g"
      ],
      "instructions": [],
      "cookingTime": 0,
      "servings": 2,
      "difficulty": "medium",
      "category": "salad",
      "tags": ["salad", "day-to-day"]
    },
    {
      "id": 79,
      "name": "Gurkenkracher Salat",
      "description": "EatSmarter! 3/2024, 80",
      "ingredients": [
        "Paprika: 200g",
        "Salz: 2g",
        "Gurke: 400g",
        "Kichererbsen: 60g",
        "Gemuesebruehe: 40g",
        "Reisessig: 30g",
        "Olivenoel: 60g",
        "Haselnusskerne: 40g",
        "Reisnudeln: 100g",
        "Dill: 5g",
        "Minze: 5g"
      ],
      "instructions": [],
      "cookingTime": 0,
      "servings": 2,
      "difficulty": "medium",
      "category": "salad",
      "tags": ["salad", "day-to-day"]
    },
    {
      "id": 80,
      "name": "Double Mac and Cheese",
      "description": "slowly veggie! 7, 96",
      "ingredients": [],
      "instructions": [],
      "cookingTime": 0,
      "servings": 0,
      "difficulty": "medium",
      "category": "other",
      "tags": ["day-to-day"]
    }
  ]
}
